{"name":"services/6F81-5844-456A/skus/13D8-09B4-9EB7","skuId":"13D8-09B4-9EB7","description":"Preemptible N2D AMD Custom Extended Instance Ram running in Los Angeles","category":{"serviceDisplayName":"Compute Engine","resourceFamily":"Compute","resourceGroup":"RAM","usageType":"Preemptible"},"serviceRegions":["us-west2"],"pricingInfo":[{"summary":"","pricingExpression":{"usageUnit":"GiBy.h","usageUnitDescription":"gibibyte hour","baseUnit":"By.s","baseUnitDescription":"byte second","baseUnitConversionFactor":3865470566400,"displayQuantity":1,"tieredRates":[{"startUsageAmount":0,"unitPrice":{"currencyCode":"USD","units":"0","nanos":2305000}}]},"currencyConversionRate":1,"effectiveTime":"2020-12-02T11:52:52.691Z"}],"serviceProviderName":"Google","geoTaxonomy":{"type":"REGIONAL","regions":["us-west2"]}}