{"name":"services/6F81-5844-456A/skus/ED07-FCC0-BB7D","skuId":"ED07-FCC0-BB7D","description":"Commitment: Compute optimized Ram running in Frankfurt for 1 Year","category":{"serviceDisplayName":"Compute Engine","resourceFamily":"Compute","resourceGroup":"RAM","usageType":"Commit1Yr"},"serviceRegions":["europe-west3"],"pricingInfo":[{"summary":"","pricingExpression":{"usageUnit":"GiBy.h","usageUnitDescription":"gibibyte hour","baseUnit":"By.s","baseUnitDescription":"byte second","baseUnitConversionFactor":3865470566400,"displayQuantity":1,"tieredRates":[{"startUsageAmount":0,"unitPrice":{"currencyCode":"USD","units":"0","nanos":3693000}}]},"currencyConversionRate":1,"effectiveTime":"2020-12-02T11:52:52.691Z"}],"serviceProviderName":"Google","geoTaxonomy":{"type":"REGIONAL","regions":["europe-west3"]}}