{"name":"services/6F81-5844-456A/skus/1D26-3C97-3922","skuId":"1D26-3C97-3922","description":"Network Vpn Internet Ingress from Central America to Las Vegas","category":{"serviceDisplayName":"Compute Engine","resourceFamily":"Network","resourceGroup":"VPNInternetIngress","usageType":"OnDemand"},"serviceRegions":["us-west4"],"pricingInfo":[{"summary":"","pricingExpression":{"usageUnit":"GiBy","usageUnitDescription":"gibibyte","baseUnit":"By","baseUnitDescription":"byte","baseUnitConversionFactor":1073741824,"displayQuantity":1,"tieredRates":[{"startUsageAmount":0,"unitPrice":{"currencyCode":"USD","units":"0","nanos":0}}]},"currencyConversionRate":1,"effectiveTime":"2020-12-02T11:52:52.691Z"}],"serviceProviderName":"Google"}