{"name":"services/6F81-5844-456A/skus/AAEB-2D19-B7E5","skuId":"AAEB-2D19-B7E5","description":"Network CDN North America Intra-Region Cache Fill","category":{"serviceDisplayName":"Compute Engine","resourceFamily":"Network","resourceGroup":"CDNCacheFill","usageType":"OnDemand"},"serviceRegions":["us-central1","us-east1","us-west1","us-west3"],"pricingInfo":[{"summary":"","pricingExpression":{"usageUnit":"GiBy","usageUnitDescription":"gibibyte","baseUnit":"By","baseUnitDescription":"byte","baseUnitConversionFactor":1073741824,"displayQuantity":1,"tieredRates":[{"startUsageAmount":0,"unitPrice":{"currencyCode":"USD","units":"0","nanos":10000000}}]},"currencyConversionRate":1,"effectiveTime":"2020-12-02T11:52:52.691Z"}],"serviceProviderName":"Google"}