{"name":"services/6F81-5844-456A/skus/506E-E4F0-07F7","skuId":"506E-E4F0-07F7","description":"Licensing Fee for Windows Server 2016 Nano on f1-micro","category":{"serviceDisplayName":"Compute Engine","resourceFamily":"License","resourceGroup":"Windows2016","usageType":"OnDemand"},"serviceRegions":["global"],"pricingInfo":[{"summary":"","pricingExpression":{"usageUnit":"h","usageUnitDescription":"hour","baseUnit":"s","baseUnitDescription":"second","baseUnitConversionFactor":3600,"displayQuantity":1,"tieredRates":[{"startUsageAmount":0,"unitPrice":{"currencyCode":"USD","units":"0","nanos":23000000}}]},"currencyConversionRate":1,"effectiveTime":"2020-12-02T11:52:52.691Z"}],"serviceProviderName":"Google","geoTaxonomy":{"type":"GLOBAL","regions":[]}}